py2dm/__init__.py
py2dm/_entities.py
py2dm/_read.py
py2dm/_typing.py
py2dm/_write.py
py2dm/errors.py
py2dm/py.typed
py2dm/utils.py
py2dm/_parser/__init__.py
py2dm/_parser/_cparser.cp39-win_amd64.pyd
py2dm/_parser/_cparser.pyi
py2dm/_parser/_pyparser.py
py2dm-0.2.2.dist-info/LICENSE
py2dm-0.2.2.dist-info/METADATA
py2dm-0.2.2.dist-info/WHEEL
py2dm-0.2.2.dist-info/top_level.txt
py2dm-0.2.2.dist-info/RECORD
