Metadata-Version: 2.1
Name: py2dm
Version: 0.2.2
Summary: Read and write 2DM mesh files
Home-page: https://github.com/leonhard-s/Py2DM
Author: Leonhard S.
Keywords: mesh 2dm
Classifier: Development Status :: 4 - Beta
Classifier: Intended Audience :: Developers
Classifier: License :: OSI Approved :: MIT License
Classifier: Programming Language :: Python :: 3.6
Classifier: Programming Language :: Python :: 3.7
Classifier: Programming Language :: Python :: 3.8
Classifier: Programming Language :: Python :: 3.9
Classifier: Programming Language :: Python :: 3.10
Classifier: Programming Language :: Python :: 3 :: Only
License-File: LICENSE
